jsonl_to_conll/__init__.py
jsonl_to_conll/cli.py
jsonl_to_conll/convert.py
jsonl_to_conll/io.py
jsonl_to_conll-1.0.2.dist-info/LICENSE
jsonl_to_conll-1.0.2.dist-info/METADATA
jsonl_to_conll-1.0.2.dist-info/WHEEL
jsonl_to_conll-1.0.2.dist-info/entry_points.txt
jsonl_to_conll-1.0.2.dist-info/top_level.txt
jsonl_to_conll-1.0.2.dist-info/RECORD
